cli/__init__.py
cli/github_migration_cli.py
cli/nforge_parser_cli.py
migration/__init__.py
migration/exception.py
migration/github.py
migration/helper.py
migration/nforge.py
nforge_migration-1.1.0.post1.dist-info/DESCRIPTION.rst
nforge_migration-1.1.0.post1.dist-info/METADATA
nforge_migration-1.1.0.post1.dist-info/RECORD
nforge_migration-1.1.0.post1.dist-info/WHEEL
nforge_migration-1.1.0.post1.dist-info/entry_points.txt
nforge_migration-1.1.0.post1.dist-info/metadata.json
nforge_migration-1.1.0.post1.dist-info/top_level.txt
