Metadata-Version: 2.0
Name: nforge-migration
Version: 1.1.0.post1
Summary: Migrate nForge project to GitHub
Home-page: https://github.com/naver/devcenter-open-project-migration
Author: Taehwan Kim
Author-email: maxtortime@navercorp.com
License: Apache License, Version 2.0
Keywords: nForge migration github naver open_project
Platform: UNKNOWN
Classifier: Development Status :: 5 - Production/Stable
Classifier: Topic :: Utilities
Classifier: Topic :: System :: Archiving :: Backup
Classifier: Topic :: Text Processing :: Markup :: XML
Classifier: Environment :: Console
Classifier: Natural Language :: Korean
Classifier: Operating System :: Microsoft :: Windows
Classifier: Operating System :: MacOS
Classifier: Operating System :: POSIX :: Linux
Classifier: Programming Language :: Python :: 2.7
Classifier: Programming Language :: Python :: 3
Classifier: Programming Language :: Python :: 3.3
Classifier: Programming Language :: Python :: 3.4
Classifier: Programming Language :: Python :: 3.5
Requires-Dist: beautifulsoup4 (==4.5.1)
Requires-Dist: click (==6.6)
Requires-Dist: future (==0.16.0)
Requires-Dist: github3.py (==0.9.6)
Requires-Dist: lxml (==3.6.4)
Requires-Dist: requests (==2.11.1)
Requires-Dist: requests-toolbelt (==0.7.0)
Requires-Dist: tqdm (==4.9.0)
